README.rst
setup.py
gtr/__init__.py
gtr.egg-info/PKG-INFO
gtr.egg-info/SOURCES.txt
gtr.egg-info/dependency_links.txt
gtr.egg-info/not-zip-safe
gtr.egg-info/requires.txt
gtr.egg-info/top_level.txt
gtr/services/__init__.py
gtr/services/base.py
gtr/services/funds.py
gtr/services/organisations.py
gtr/services/persons.py
gtr/services/projects.py
gtr/services/publications.py
tests/__init__.py
tests/test_base.py
tests/test_funds.py
tests/test_organisations.py
tests/test_persons.py
tests/test_projects.py
tests/test_publications.py