Metadata-Version: 1.1
Name: gtr
Version: 0.1.1
Summary: A Python interface to the Gateway To Research GTR-2 API.
Home-page: http://github.com/nestauk/gtr
Author: James Gardiner
Author-email: james.gardiner@nesta.org.uk
License: APACHEV2.0
Download-URL: https://github.com/nesta/gtr/tarball/0.1
Platform: UNKNOWN
Classifier: Operating System :: OS Independent
Classifier: Programming Language :: Python
Classifier: Programming Language :: Python :: 3
Classifier: Programming Language :: Python :: 3.3
Classifier: Programming Language :: Python :: 3.4
Classifier: Programming Language :: Python :: 3.5
